django_marionettejs-0.1.1.dist-info/DESCRIPTION.rst
django_marionettejs-0.1.1.dist-info/METADATA
django_marionettejs-0.1.1.dist-info/RECORD
django_marionettejs-0.1.1.dist-info/WHEEL
django_marionettejs-0.1.1.dist-info/metadata.json
django_marionettejs-0.1.1.dist-info/top_level.txt
marionettejs/__init__.py
marionettejs/admin.py
marionettejs/models.py
marionettejs/tests.py
marionettejs/views.py
marionettejs/static/css/bootstrap-theme.css
marionettejs/static/css/bootstrap-theme.css.map
marionettejs/static/css/bootstrap-theme.min.css
marionettejs/static/css/bootstrap.css
marionettejs/static/css/bootstrap.css.map
marionettejs/static/css/bootstrap.min.css
marionettejs/static/js/backbone-min.map
marionettejs/static/js/backbone.babysitter.js
marionettejs/static/js/backbone.js
marionettejs/static/js/backbone.marionette.map
marionettejs/static/js/backbone.marionette.min.js
marionettejs/static/js/backbone.wreqr.js
marionettejs/static/js/bootstrap.min.js
marionettejs/static/js/csrf_token.js
marionettejs/static/js/jquery.js
marionettejs/static/js/json2.js
marionettejs/static/js/underscore.js
marionettejs/templates/base.html
