Metadata-Version: 2.0
Name: django-marionettejs
Version: 0.1.1
Summary: A simple Django app to be extends for easier backbone development, it provides a base template to inherit
Home-page: UNKNOWN
Author: Tim Hsu
Author-email: tim.yellow@gmail.com
License: BSD License
Platform: UNKNOWN
Classifier: Environment :: Web Environment
Classifier: Framework :: Django
Classifier: Intended Audience :: Developers
Classifier: License :: OSI Approved :: BSD License
Classifier: Operating System :: OS Independent
Classifier: Programming Language :: Python
Requires-Dist: django-compressor
